{
    "id": "nucpaballoonsapi",
    "title": "Nucpa Balloons API",
    "description": "A comprehensive API for the Nucpa Balloons project",
    "repoUrl": "https://github.com/aabdoo23/NucpaBalloonsApi",
    "liveUrl": "https://nucpa-balloons.runasp.net/swagger/index.html",
    "techStack": [
        "C#",
        "ASP.NET Core",
        "Entity Framework",
        "SQL Server",
        "Swagger"
    ],
    "structure": {
        "root": "NucpaBalloonsApi",
        "children": [
            {
                "name": ".gitattributes",
                "type": "file"
            },
            {
                "name": ".gitignore",
                "type": "file"
            },
            {
                "name": "Controllers",
                "type": "directory",
                "children": [
                    {
                        "name": "AdminController.cs",
                        "type": "file"
                    },
                    {
                        "name": "AdminSettingsController.cs",
                        "type": "file"
                    },
                    {
                        "name": "BalloonController.cs",
                        "type": "file"
                    },
                    {
                        "name": "ProblemBalloonMapController.cs",
                        "type": "file"
                    },
                    {
                        "name": "RoomController.cs",
                        "type": "file"
                    },
                    {
                        "name": "TeamController.cs",
                        "type": "file"
                    },
                    {
                        "name": "ToiletRequestController.cs",
                        "type": "file"
                    }
                ]
            },
            {
                "name": "Hubs",
                "type": "directory",
                "children": [
                    {
                        "name": "BalloonHub.cs",
                        "type": "file"
                    }
                ]
            },
            {
                "name": "Interfaces",
                "type": "directory",
                "children": [
                    {
                        "name": "Repositories",
                        "type": "directory",
                        "children": [
                            {
                                "name": "Common",
                                "type": "directory",
                                "children": [
                                    {
                                        "name": "IBaseRepository.cs",
                                        "type": "file"
                                    }
                                ]
                            },
                            {
                                "name": "IRoomRepository.cs",
                                "type": "file"
                            },
                            {
                                "name": "ITeamRepository.cs",
                                "type": "file"
                            }
                        ]
                    },
                    {
                        "name": "Services",
                        "type": "directory",
                        "children": [
                            {
                                "name": "IAdminService.cs",
                                "type": "file"
                            },
                            {
                                "name": "IAdminSettingsService.cs",
                                "type": "file"
                            },
                            {
                                "name": "IBalloonService.cs",
                                "type": "file"
                            },
                            {
                                "name": "ICodeforcesApiService.cs",
                                "type": "file"
                            },
                            {
                                "name": "IProblemBalloonMapService.cs",
                                "type": "file"
                            },
                            {
                                "name": "IRoomsService.cs",
                                "type": "file"
                            },
                            {
                                "name": "ITeamsService.cs",
                                "type": "file"
                            },
                            {
                                "name": "IToiletRequestService.cs",
                                "type": "file"
                            }
                        ]
                    }
                ]
            },
            {
                "name": "Migrations",
                "type": "directory",
                "children": [
                    {
                        "name": "20250402001302_first-again.Designer.cs",
                        "type": "file"
                    },
                    {
                        "name": "20250402001302_first-again.cs",
                        "type": "file"
                    },
                    {
                        "name": "20250403040857_room-fix.Designer.cs",
                        "type": "file"
                    },
                    {
                        "name": "20250403040857_room-fix.cs",
                        "type": "file"
                    },
                    {
                        "name": "20250403173302_toilet-requests.Designer.cs",
                        "type": "file"
                    },
                    {
                        "name": "20250403173302_toilet-requests.cs",
                        "type": "file"
                    },
                    {
                        "name": "NucpaDbContextModelSnapshot.cs",
                        "type": "file"
                    }
                ]
            },
            {
                "name": "Models",
                "type": "directory",
                "children": [
                    {
                        "name": "Codeforces",
                        "type": "directory",
                        "children": [
                            {
                                "name": "ApiResponse.cs",
                                "type": "file"
                            },
                            {
                                "name": "Contest.cs",
                                "type": "file"
                            },
                            {
                                "name": "ContestStandings.cs",
                                "type": "file"
                            },
                            {
                                "name": "Member.cs",
                                "type": "file"
                            },
                            {
                                "name": "Party.cs",
                                "type": "file"
                            },
                            {
                                "name": "Problem.cs",
                                "type": "file"
                            },
                            {
                                "name": "ProblemResult.cs",
                                "type": "file"
                            },
                            {
                                "name": "RanklistRow.cs",
                                "type": "file"
                            },
                            {
                                "name": "Submission.cs",
                                "type": "file"
                            }
                        ]
                    },
                    {
                        "name": "Common",
                        "type": "directory",
                        "children": [
                            {
                                "name": "BaseEntity.cs",
                                "type": "file"
                            },
                            {
                                "name": "StatusableEntity.cs",
                                "type": "file"
                            }
                        ]
                    },
                    {
                        "name": "DTOs",
                        "type": "directory",
                        "children": [
                            {
                                "name": "Admin",
                                "type": "directory",
                                "children": [
                                    {
                                        "name": "LoginRequestDTO.cs",
                                        "type": "file"
                                    },
                                    {
                                        "name": "LoginResponseDTO.cs",
                                        "type": "file"
                                    }
                                ]
                            },
                            {
                                "name": "AdminSettingsResponseDTO.cs",
                                "type": "file"
                            },
                            {
                                "name": "BalloonRequestDTO.cs",
                                "type": "file"
                            },
                            {
                                "name": "BalloonStatisticsDTO.cs",
                                "type": "file"
                            },
                            {
                                "name": "ToiletResponseDTO.cs",
                                "type": "file"
                            }
                        ]
                    },
                    {
                        "name": "Requests",
                        "type": "directory",
                        "children": [
                            {
                                "name": "AdminSettings",
                                "type": "directory",
                                "children": [
                                    {
                                        "name": "AdminSettingsCreateRequestDTO.cs",
                                        "type": "file"
                                    },
                                    {
                                        "name": "AdminSettingsUpdateRequestDTO.cs",
                                        "type": "file"
                                    }
                                ]
                            },
                            {
                                "name": "BalloonRequest",
                                "type": "directory",
                                "children": [
                                    {
                                        "name": "BalloonStatusUpdateRequest.cs",
                                        "type": "file"
                                    }
                                ]
                            },
                            {
                                "name": "ProblemBalloonMaps",
                                "type": "directory",
                                "children": [
                                    {
                                        "name": "ProblemBalloonMapCreateRequestDTO.cs",
                                        "type": "file"
                                    }
                                ]
                            },
                            {
                                "name": "Rooms",
                                "type": "directory",
                                "children": [
                                    {
                                        "name": "RoomCreateRequestDTO.cs",
                                        "type": "file"
                                    }
                                ]
                            },
                            {
                                "name": "Teams",
                                "type": "directory",
                                "children": [
                                    {
                                        "name": "TeamCreateRequestDTO.cs",
                                        "type": "file"
                                    }
                                ]
                            },
                            {
                                "name": "ToiletRequest",
                                "type": "directory",
                                "children": [
                                    {
                                        "name": "ToiletRequestDTO.cs",
                                        "type": "file"
                                    },
                                    {
                                        "name": "ToiletRequestStatusUpdateDTO.cs",
                                        "type": "file"
                                    }
                                ]
                            }
                        ]
                    },
                    {
                        "name": "SystemModels",
                        "type": "directory",
                        "children": [
                            {
                                "name": "AdminSettings.cs",
                                "type": "file"
                            },
                            {
                                "name": "BalloonRequest.cs",
                                "type": "file"
                            },
                            {
                                "name": "ProblemBalloonMap.cs",
                                "type": "file"
                            },
                            {
                                "name": "Room.cs",
                                "type": "file"
                            },
                            {
                                "name": "Team.cs",
                                "type": "file"
                            },
                            {
                                "name": "ToiletRequest.cs",
                                "type": "file"
                            }
                        ]
                    }
                ]
            },
            {
                "name": "NucpaBalloonsApi.csproj",
                "type": "file"
            },
            {
                "name": "NucpaBalloonsApi.http",
                "type": "file"
            },
            {
                "name": "NucpaBalloonsApi.sln",
                "type": "file"
            },
            {
                "name": "NucpaDbContext.cs",
                "type": "file"
            },
            {
                "name": "Program.cs",
                "type": "file"
            },
            {
                "name": "Properties",
                "type": "directory",
                "children": [
                    {
                        "name": "launchSettings.json",
                        "type": "file"
                    }
                ]
            },
            {
                "name": "Repositories",
                "type": "directory",
                "children": [
                    {
                        "name": "Common",
                        "type": "directory",
                        "children": [
                            {
                                "name": "BaseRepository.cs",
                                "type": "file"
                            }
                        ]
                    },
                    {
                        "name": "RoomRepository.cs",
                        "type": "file"
                    },
                    {
                        "name": "TeamRepository.cs",
                        "type": "file"
                    }
                ]
            },
            {
                "name": "Services",
                "type": "directory",
                "children": [
                    {
                        "name": "AdminService.cs",
                        "type": "file"
                    },
                    {
                        "name": "AdminSettingsService.cs",
                        "type": "file"
                    },
                    {
                        "name": "BalloonService.cs",
                        "type": "file"
                    },
                    {
                        "name": "BalloonUpdateService.cs",
                        "type": "file"
                    },
                    {
                        "name": "CodeforcesApiService.cs",
                        "type": "file"
                    },
                    {
                        "name": "ProblemBalloonMapService.cs",
                        "type": "file"
                    },
                    {
                        "name": "RoomsService.cs",
                        "type": "file"
                    },
                    {
                        "name": "TeamsService.cs",
                        "type": "file"
                    },
                    {
                        "name": "ToiletRequestService.cs",
                        "type": "file"
                    }
                ]
            },
            {
                "name": "appsettings.Development.json",
                "type": "file"
            },
            {
                "name": "appsettings.json",
                "type": "file"
            },
            {
                "name": "package-lock.json",
                "type": "file"
            },
            {
                "name": "package.json",
                "type": "file"
            }
        ]
    },
    "images": []
}